{
    "receiptStandards": [
        {
            "required_data": "Supplier business name",
            "travel_non_travel_both": "Both",
            "expense_type": "Hotel, Flight, Train, Restaurant, Taxi, Office supplies, Software, Equipment, Telecommunications",
            "icp_name": "上海炎焰企业管理有限公司, GoGlobal China",
            "mandatory_optional": "Mandatory",
            "rule": "Receipt must show the business name of the supplier/vendor providing the goods or services"
        },
        {
            "required_data": "Transaction date",
            "travel_non_travel_both": "Both",
            "expense_type": "Hotel, Flight, Train, Restaurant, Taxi, Office supplies, Software, Equipment, Telecommunications",
            "icp_name": "上海炎焰企业管理有限公司, GoGlobal China",
            "mandatory_optional": "Mandatory",
            "rule": "Receipt must show the date when the expense was incurred"
        },
        {
            "required_data": "Total amount in local currency",
            "travel_non_travel_both": "Both",
            "expense_type": "Hotel, Flight, Train, Restaurant, Taxi, Office supplies, Software, Equipment",
            "icp_name": "上海炎焰企业管理有限公司, GoGlobal China",
            "mandatory_optional": "Mandatory",
            "rule": "Receipt must display the total cost including all taxes and fees"
        },
        {
            "required_data": "Item description",
            "travel_non_travel_both": "Both",
            "expense_type": "Hotel, Flight, Train, Restaurant, Taxi, Office supplies, Software, Equipment, Telecommunications",
            "icp_name": "上海炎焰企业管理有限公司, GoGlobal China",
            "mandatory_optional": "Mandatory",
            "rule": "Receipt must specify the goods or services purchased with detailed breakdown"
        },
        {
            "required_data": "ICP company name on fapiao",
            "travel_non_travel_both": "Non-Travel",
            "expense_type": "Office supplies, Software, Equipment",
            "icp_name": "上海炎焰企业管理有限公司",
            "mandatory_optional": "Mandatory",
            "rule": "Invoice title/header must be that of the Local Employer: Company Name 公司名称: 上海炎焰企业管理有限公司"
        },
        {
            "required_data": "ICP tax identification number",
            "travel_non_travel_both": "Non-Travel",
            "expense_type": "Office supplies, Software, Equipment",
            "icp_name": "上海炎焰企业管理有限公司",
            "mandatory_optional": "Mandatory",
            "rule": "Must show Company Tax Code 纳税人识别号: 913101153123807359"
        },
        {
            "required_data": "ICP company address and phone",
            "travel_non_travel_both": "Non-Travel",
            "expense_type": "Office supplies, Software, Equipment",
            "icp_name": "上海炎焰企业管理有限公司",
            "mandatory_optional": "Mandatory",
            "rule": "Must show Company Address and Landline 地址电话: 中国(上海)自由贸易试验区临港新片区鸿音路3156弄8号4层121室 021-62365280"
        },
        {
            "required_data": "ICP bank details",
            "travel_non_travel_both": "Non-Travel",
            "expense_type": "Office supplies, Software, Equipment",
            "icp_name": "上海炎焰企业管理有限公司",
            "mandatory_optional": "Mandatory",
            "rule": "Must show Bank Name: 开户银行:中国工商银行股份有限公司上海漕河泾开发区支行 and Bank Account Number 银行账号: 100126630920 0329 328"
        },
        {
            "required_data": "Employee name as passenger/guest",
            "travel_non_travel_both": "Travel",
            "expense_type": "Hotel, Flight, Train",
            "icp_name": "上海炎焰企业管理有限公司, GoGlobal China",
            "mandatory_optional": "Mandatory",
            "rule": "For flights: itinerary must show employee name. For hotels: detailed bill must show guest name. For trains: ticket must show employee name"
        },
        {
            "required_data": "Employee name on telecommunications invoice",
            "travel_non_travel_both": "Non-Travel",
            "expense_type": "Telecommunications",
            "icp_name": "上海炎焰企业管理有限公司, GoGlobal China",
            "mandatory_optional": "Optional",
            "rule": "Telephone/Mobile phone fapiaos can be in the name of the employee"
        },
        {
            "required_data": "VAT special invoice seal",
            "travel_non_travel_both": "Non-Travel",
            "expense_type": "Office supplies, Software, Equipment",
            "icp_name": "上海炎焰企业管理有限公司, GoGlobal China",
            "mandatory_optional": "Optional",
            "rule": "Where possible, workers should collect a VAT special invoice (增值税专用发票) with special seal for invoices"
        },
        {
            "required_data": "Official tax bureau invoice number",
            "travel_non_travel_both": "Travel",
            "expense_type": "Taxi",
            "icp_name": "上海炎焰企业管理有限公司, GoGlobal China",
            "mandatory_optional": "Mandatory",
            "rule": "For taxi hailing apps, only official invoice of tax bureau marked with invoice number can be used as basis for reimbursement"
        },
        {
            "required_data": "What, Where, When information",
            "travel_non_travel_both": "Both",
            "expense_type": "Hotel, Flight, Train, Restaurant, Taxi, Office supplies, Software, Equipment, Telecommunications",
            "icp_name": "GoGlobal China",
            "mandatory_optional": "Mandatory",
            "rule": "Receipts must show: What (expense type/category), Where (place of expense), When (time of expense)"
        }
    ],
    "compliancePoliciesGrossUpRelated": [
        {
            "travel_non_travel_both": "Travel",
            "expense_type": "Flight, Train, Bus, Taxi",
            "icp_name": "上海炎焰企业管理有限公司, GoGlobal China",
            "gross_up": false,
            "gross_up_rule": "Transportation (airline tickets, train, bus, taxi etc.) are tax exempt for both employer and worker"
        },
        {
            "travel_non_travel_both": "Travel",
            "expense_type": "Hotel",
            "icp_name": "上海炎焰企业管理有限公司, GoGlobal China",
            "gross_up": false,
            "gross_up_rule": "Hotel, Office Rent, Meeting Room Rent are tax exempt for both employer and worker"
        },
        {
            "travel_non_travel_both": "Travel",
            "expense_type": "Restaurant",
            "icp_name": "上海炎焰企业管理有限公司, GoGlobal China",
            "gross_up": true,
            "gross_up_rule": "Personal Meal during Business Trips generally not exceeding 150 RMB/day/person is tax exempt. Set rates: 1st tier cities (Beijing, Shanghai, Guangzhou, Shenzhen) 200 yuan per day (80 yuan per meal lunch/dinner), new 1st tier and 2nd tier cities 150 yuan per day (60 yuan per meal), 3rd tier cities 100 yuan per day (40 yuan per meal). Meals exceeding limit treated as entertaining customers or reimbursed after withholding personal income tax"
        },
        {
            "travel_non_travel_both": "Travel",
            "expense_type": "Mileage",
            "icp_name": "上海炎焰企业管理有限公司, GoGlobal China",
            "gross_up": true,
            "gross_up_rule": "Fuel fees on cars not owned by employer: Usually paid as taxable Car Allowance between RMB 1.5-2.5 per KM. Common rate 1.5 to 2.5 yuan per kilometer"
        },
        {
            "travel_non_travel_both": "Travel",
            "expense_type": "Tolls, Parking fees",
            "icp_name": "上海炎焰企业管理有限公司, GoGlobal China",
            "gross_up": true,
            "gross_up_rule": "Parking fees and highway tolls: Either Corporate Income Tax (25%) or Individual Income Tax applied if cannot prove expenses for entertaining customers"
        },
        {
            "travel_non_travel_both": "Travel",
            "expense_type": "Per diem (no invoices)",
            "icp_name": "上海炎焰企业管理有限公司, GoGlobal China",
            "gross_up": true,
            "gross_up_rule": "Per Diem (no invoices) subject to Individual Income Tax, except for exemptions which apply to expat workers"
        },
        {
            "travel_non_travel_both": "Travel",
            "expense_type": "International per diem",
            "icp_name": "上海炎焰企业管理有限公司, GoGlobal China",
            "gross_up": true,
            "gross_up_rule": "Per diem rates subject to Individual Income tax, except for exemptions which apply to expat workers"
        },
        {
            "travel_non_travel_both": "Non-Travel",
            "expense_type": "Office supplies",
            "icp_name": "上海炎焰企业管理有限公司, GoGlobal China",
            "gross_up": false,
            "gross_up_rule": "Office Supplies (knifes, folders, toilet tissues, printer) are tax exempt for both employer and worker"
        },
        {
            "travel_non_travel_both": "Non-Travel",
            "expense_type": "Office equipment",
            "icp_name": "上海炎焰企业管理有限公司, GoGlobal China",
            "gross_up": false,
            "gross_up_rule": "Office equipment (laptops, etc.), Work-protection tools, Fixed assets/furniture/electrical appliances are tax exempt for both employer and worker"
        },
        {
            "travel_non_travel_both": "Non-Travel",
            "expense_type": "Electronic products and communication equipment",
            "icp_name": "上海炎焰企业管理有限公司, GoGlobal China",
            "gross_up": false,
            "gross_up_rule": "Electronic products and accessories, communication equipment (routers, cell phones, except gifts to employees) are tax exempt for both employer and worker"
        },
        {
            "travel_non_travel_both": "Non-Travel",
            "expense_type": "Telecommunications registered under company",
            "icp_name": "上海炎焰企业管理有限公司, GoGlobal China",
            "gross_up": false,
            "gross_up_rule": "Telephone/communication fees on devices registered under company name are tax exempt for both employer and worker"
        },
        {
            "travel_non_travel_both": "Non-Travel",
            "expense_type": "Telecommunications registered under individual",
            "icp_name": "上海炎焰企业管理有限公司, GoGlobal China",
            "gross_up": true,
            "gross_up_rule": "Telephone/communication fee invoices with individual name (SIM card NOT registered under company name) are subject to Individual Income Tax for worker"
        },
        {
            "travel_non_travel_both": "Non-Travel",
            "expense_type": "Network IT service",
            "icp_name": "上海炎焰企业管理有限公司, GoGlobal China",
            "gross_up": false,
            "gross_up_rule": "Network IT service is tax exempt for both employer and worker"
        },
        {
            "travel_non_travel_both": "Non-Travel",
            "expense_type": "Government-issued receipts",
            "icp_name": "上海炎焰企业管理有限公司, GoGlobal China",
            "gross_up": false,
            "gross_up_rule": "Government-issued receipts (visa fees etc.) are tax exempt for both employer and worker"
        },
        {
            "travel_non_travel_both": "Both",
            "expense_type": "Entertainment service fees for team building",
            "icp_name": "上海炎焰企业管理有限公司, GoGlobal China",
            "gross_up": true,
            "gross_up_rule": "Entertainment service fees for team building activities (dinners, beverages, KTV, tourist attractions, refreshments, food, cigarettes) subject to Corporate Income Tax (25%) for employer, tax exempt for worker"
        },
        {
            "travel_non_travel_both": "Both",
            "expense_type": "Entertainment expenses with clients",
            "icp_name": "上海炎焰企业管理有限公司, GoGlobal China",
            "gross_up": true,
            "gross_up_rule": "Entertainment expenses with clients (meals, beverages, spirits, tobacco, KTV, tourist attractions, refreshments) subject to Corporate Income Tax (25%) for employer, tax exempt for worker"
        },
        {
            "travel_non_travel_both": "Non-Travel",
            "expense_type": "Small and medium appliances",
            "icp_name": "上海炎焰企业管理有限公司, GoGlobal China",
            "gross_up": true,
            "gross_up_rule": "Small and medium-sized appliances (microwave ovens, except gifts to employees) subject to Corporate Income Tax (25%) for employer, tax exempt for worker"
        },
        {
            "travel_non_travel_both": "Non-Travel",
            "expense_type": "Gifts and shopping cards for customers",
            "icp_name": "上海炎焰企业管理有限公司, GoGlobal China",
            "gross_up": true,
            "gross_up_rule": "Gifts and shopping cards for customers subject to Corporate Income Tax (25%) for employer, tax exempt for worker"
        },
        {
            "travel_non_travel_both": "Non-Travel",
            "expense_type": "Shopping cards and gifts for employees",
            "icp_name": "上海炎焰企业管理有限公司, GoGlobal China",
            "gross_up": true,
            "gross_up_rule": "Shopping cards and red packets (Hong Bao) for employees as gifts subject to Corporate Income Tax (25%) for employer AND Individual Income Tax for worker"
        },
        {
            "travel_non_travel_both": "Non-Travel",
            "expense_type": "Annual Medical Check",
            "icp_name": "上海炎焰企业管理有限公司, GoGlobal China",
            "gross_up": true,
            "gross_up_rule": "Annual Medical Check subject to Corporate Income Tax (25%) for employer AND Individual Income Tax for worker"
        },
        {
            "travel_non_travel_both": "Non-Travel",
            "expense_type": "Gym",
            "icp_name": "上海炎焰企业管理有限公司, GoGlobal China",
            "gross_up": true,
            "gross_up_rule": "Gym expenses subject to Corporate Income Tax (25%) for employer AND Individual Income Tax for worker"
        },
        {
            "travel_non_travel_both": "Non-Travel",
            "expense_type": "Daily cleaning and hygiene products",
            "icp_name": "上海炎焰企业管理有限公司, GoGlobal China",
            "gross_up": true,
            "gross_up_rule": "Daily cleaning/hygiene products (dishwashing liquid, cosmetics) either Corporate Income Tax (25%) or Individual Income Tax applied"
        },
        {
            "travel_non_travel_both": "Non-Travel",
            "expense_type": "Sports equipment",
            "icp_name": "上海炎焰企业管理有限公司, GoGlobal China",
            "gross_up": true,
            "gross_up_rule": "Sports equipment either Corporate Income Tax (25%) or Individual Income Tax applied"
        },
        {
            "travel_non_travel_both": "Non-Travel",
            "expense_type": "Toys",
            "icp_name": "上海炎焰企业管理有限公司, GoGlobal China",
            "gross_up": true,
            "gross_up_rule": "Toys either Corporate Income Tax (25%) or Individual Income Tax applied"
        },
        {
            "travel_non_travel_both": "Non-Travel",
            "expense_type": "Small non-commonly used appliances",
            "icp_name": "上海炎焰企业管理有限公司, GoGlobal China",
            "gross_up": true,
            "gross_up_rule": "Small non-commonly used appliances (juicers) depends on specific appliance - verify before buying"
        },
        {
            "travel_non_travel_both": "Non-Travel",
            "expense_type": "Marketing activities over CNY30,000",
            "icp_name": "GoGlobal China",
            "gross_up": true,
            "gross_up_rule": "Marketing Activity expenses with single tax fapiao amount bigger than CNY30,000 (about USD4500) without service contract may be challenged by tax bureau"
        },
        {
            "travel_non_travel_both": "Non-Travel",
            "expense_type": "Entertainment expenses requiring corporate tax pass-through",
            "icp_name": "GoGlobal China",
            "gross_up": true,
            "gross_up_rule": "If GoGlobal required to process entertainment expense reimbursement, involved corporate income tax (15%-25%) passed to end client"
        },
        {
            "travel_non_travel_both": "Both",
            "expense_type": "Business expenses without proper fapiao",
            "icp_name": "上海炎焰企业管理有限公司, GoGlobal China",
            "gross_up": true,
            "gross_up_rule": "Claims without proper Fapiao considered as employee income and subjected to personal income tax with monthly salary. Tax rate based on individual's accumulated annual income from 3% to 45%"
        }
    ],
    "compliancePoliciesAdditionalInfoRelated": [
        {
            "travel_non_travel_both": "Both",
            "expense_type": "Hotel, Flight, Train, Restaurant, Taxi, Office supplies, Software, Equipment, Telecommunications",
            "icp_name": "上海炎焰企业管理有限公司",
            "additional_info_required": true,
            "additional_info_rule": "Original invoice and deduction sheet must be sent to Local Employer's Dalian Branch: Name: Sylvia Jiang, Office Address: 大连市高新园区高新街9号晟辉科技大厦703室, Tel.: +86 17615158127 or 0411-81760355 dial 808. Use S.F. Express paid by shipper and collect express fee invoice for reimbursement"
        },
        {
            "travel_non_travel_both": "Both",
            "expense_type": "Hotel, Flight, Train, Restaurant, Taxi, Office supplies, Software, Equipment, Telecommunications",
            "icp_name": "上海炎焰企业管理有限公司",
            "additional_info_required": true,
            "additional_info_rule": "Business expenses must be submitted within 4 months from date of issuance. Invoices cannot be used across years"
        },
        {
            "travel_non_travel_both": "Both",
            "expense_type": "All expenses",
            "icp_name": "上海炎焰企业管理有限公司",
            "additional_info_required": true,
            "additional_info_rule": "Manager approval required. Submit expense reimbursement form to direct manager with Local Employer cc'd payroll.all@talentbankglobal.com, indicating total amount in email body"
        },
        {
            "travel_non_travel_both": "Both",
            "expense_type": "All expenses",
            "icp_name": "上海炎焰企业管理有限公司",
            "additional_info_required": true,
            "additional_info_rule": "Forward approved emails/documents and completed expense reimbursement template to payroll.all@talentbankglobal.com before 5th of month"
        },
        {
            "travel_non_travel_both": "Both",
            "expense_type": "All expenses",
            "icp_name": "上海炎焰企业管理有限公司",
            "additional_info_required": true,
            "additional_info_rule": "Original invoices must be submitted before 20th of month according to local employer's invoice filing guidelines"
        },
        {
            "travel_non_travel_both": "Both",
            "expense_type": "All foreign currency expenses",
            "icp_name": "上海炎焰企业管理有限公司, GoGlobal China",
            "additional_info_required": true,
            "additional_info_rule": "Exchange rate documentation required - use spot exchange purchase price issued by Bank of China on first working day of month after returning from business trip. Foreign currency expenses must be entered line by line according to invoices"
        },
        {
            "travel_non_travel_both": "Travel",
            "expense_type": "Hotel",
            "icp_name": "上海炎焰企业管理有限公司, GoGlobal China",
            "additional_info_required": true,
            "additional_info_rule": "Hotel detailed bill required along with fapiao showing length of stay"
        },
        {
            "travel_non_travel_both": "Travel",
            "expense_type": "Flight",
            "icp_name": "上海炎焰企业管理有限公司, GoGlobal China",
            "additional_info_required": true,
            "additional_info_rule": "Air ticket itinerary required as auxiliary certificate showing round trip air ticket, ticket itinerary. For travel agency purchases: invoice with worker name, round trip city and time period required"
        },
        {
            "travel_non_travel_both": "Travel",
            "expense_type": "Train",
            "icp_name": "上海炎焰企业管理有限公司, GoGlobal China",
            "additional_info_required": true,
            "additional_info_rule": "Printed paper train tickets required as proof of expense. National train ticket reimbursement certificate can be printed at station ticket window and automatic ticket vending machines"
        },
        {
            "travel_non_travel_both": "Travel",
            "expense_type": "Taxi with ride-hailing apps",
            "icp_name": "上海炎焰企业管理有限公司, GoGlobal China",
            "additional_info_required": true,
            "additional_info_rule": "For Didi or other ride-hailing apps: trip details/itinerary required along with official tax bureau invoice. Exception: \"Didi Chuxing\" can provide \"car-hailing service fee\" invoices for express/special cars"
        },
        {
            "travel_non_travel_both": "Travel",
            "expense_type": "Mileage with personal vehicle",
            "icp_name": "上海炎焰企业管理有限公司, GoGlobal China",
            "additional_info_required": true,
            "additional_info_rule": "Business justification required proving expenses for entertaining customers. Personal car license plate number on invoice cannot be reimbursed directly"
        },
        {
            "travel_non_travel_both": "Travel",
            "expense_type": "Business travel subsidy rates",
            "icp_name": "上海炎焰企业管理有限公司, GoGlobal China",
            "additional_info_required": true,
            "additional_info_rule": "Documentation of city tier classification required for per diem rates: 1st tier (Beijing, Shanghai, Guangzhou, Shenzhen), new 1st tier and 2nd tier cities listed, 3rd tier (all other cities)"
        },
        {
            "travel_non_travel_both": "Non-Travel",
            "expense_type": "Office supplies with generic descriptions",
            "icp_name": "上海炎焰企业管理有限公司, GoGlobal China",
            "additional_info_required": true,
            "additional_info_rule": "Detailed purchase list required if fapiao shows \"Please Refer To Detailed Purchase List\""
        },
        {
            "travel_non_travel_both": "Non-Travel",
            "expense_type": "Professional services over certain amounts",
            "icp_name": "上海炎焰企业管理有限公司, GoGlobal China",
            "additional_info_required": true,
            "additional_info_rule": "Contract required between Local Employer and provider for company services (IT services, advertising agencies). Worker must contact Local Employer 5 working days in advance"
        },
        {
            "travel_non_travel_both": "Non-Travel",
            "expense_type": "Marketing activities over CNY30,000",
            "icp_name": "GoGlobal China",
            "additional_info_required": true,
            "additional_info_rule": "Service contract required for marketing expenses with single fapiao amount over CNY30,000 to avoid tax bureau challenge"
        },
        {
            "travel_non_travel_both": "Both",
            "expense_type": "Personal information removal",
            "icp_name": "上海炎焰企业管理有限公司, GoGlobal China",
            "additional_info_required": true,
            "additional_info_rule": "Any personal information not required for reimbursement purposes should be removed before submission"
        },
        {
            "travel_non_travel_both": "Both",
            "expense_type": "Why and Who information",
            "icp_name": "GoGlobal China",
            "additional_info_required": true,
            "additional_info_rule": "Business purpose required if not shown on receipt - indicate on expense report. Business relationship to taxpayer or persons involved required if not shown on receipt - indicate on expense report"
        },
        {
            "travel_non_travel_both": "Both",
            "expense_type": "All expenses",
            "icp_name": "GoGlobal China",
            "additional_info_required": true,
            "additional_info_rule": "Expense report filled out according to internal policy required"
        },
        {
            "travel_non_travel_both": "Both",
            "expense_type": "All expenses",
            "icp_name": "GoGlobal China",
            "additional_info_required": true,
            "additional_info_rule": "Scanned copies of receipts/fapiaos submitted to HR by 5th of each month"
        },
        {
            "travel_non_travel_both": "Both",
            "expense_type": "All expenses",
            "icp_name": "GoGlobal China",
            "additional_info_required": true,
            "additional_info_rule": "Hard copy documents submitted to GoGlobal Finance Team: Room B102, Block B, Jiaozi Financial Technology Center, No. 1677, north section of Tianfu Avenue, Guixi street, Wuhou District, Chengdu, Sichuan Province, Tel: 19921181138"
        },
        {
            "travel_non_travel_both": "Both",
            "expense_type": "All expenses",
            "icp_name": "GoGlobal China",
            "additional_info_required": true,
            "additional_info_rule": "Fapiaos pasted on A4-sized paper in chronological order following expense claim form sequence, similar-sized fapiaos grouped on one sheet. Electronic fapiaos must be printed"
        }
    ]
}